{
  "nodes": [
    {"fullname": "Best Tulip", "profileurl": "https://web.facebook.com/best.tulip.73", "count": "4"},
    {"fullname": "Александр Манюшкин", "profileurl": "https://web.facebook.com/profile.php?id=100005164740949", "count": "4"},
    {"fullname": "Pavel Vorontsov","profileurl": "https://web.facebook.com/evgeny.ezopov", "count": "4"},
    {"fullname": "Edmund Tsaturyan","profileurl": "https://web.facebook.com/profile.php?id=100007475611182", "count": "4"},
    {"fullname": "Nastya Menshikova","profileurl": "https://web.facebook.com/profile.php?id=100007281094784", "count": "4"},
    {"fullname": "Anastasia Belova","profileurl": "https://web.facebook.com/profile.php?id=100005995929337", "count": "4"},
    {"fullname": "Роман Оленник","profileurl": "https://web.facebook.com/profile.php?id=100005164740949", "count": "4"},
    {"fullname": "Evgeny Ezopov","profileurl": "https://web.facebook.com/evgeny.ezopov", "count": "4"},
    {"fullname": "Dmitry DS","profileurl": "https://web.facebook.com/d.aseliverstov", "count": "4"},
    {"fullname": "Boris Love","profileurl": "https://web.facebook.com/byborqa", "count": "5"},
    {"fullname": "Sasha Maksimoff","profileurl": "https://web.facebook.com/profile.php?id=100003403122747", "count": "5"},
    {"fullname": "Brandon Mubala","profileurl": "https://web.facebook.com/brandon.mubala.5", "count": "5"},
    {"fullname": "Adam Anangisye","profileurl": "https://web.facebook.com/adam.anangisye", "count": "5"},
    {"fullname": "Rubel Hasan","profileurl": "https://web.facebook.com/rubel.hasan.5477272", "count": "1"},
    {"fullname": "Ruben Renner","profileurl": "https://web.facebook.com/ruben.renner.9", "count": "1"},
    {"fullname": "Anh Van","profileurl": "https://web.facebook.com/profile.php?id=100034035954036", "count": "1"},
    {"fullname": "Anh","profileurl": "https://web.facebook.com/profile.php?id=100034035954036", "count": "1"},
    {"fullname": "Kelly France","profileurl": "https://web.facebook.com/profile.php?id=100034035954036", "count": "1"},
    {"fullname": "Giambrone Limoncello","profileurl": "https://web.facebook.com/giambrone.limoncello", "count": "1"},
    {"fullname": "Otis Davis","profileurl": "https://web.facebook.com/otis.davis.520", "count": "1"},
    {"fullname": "Lizzy Angel","profileurl": "https://web.facebook.com/lizkoff.angel.33", "count": "7"},
    {"fullname": "David VanderLeest","profileurl": "https://web.facebook.com/davidavanderleest", "count": "12"}
  ],
  "links": [
    {"source": "Best Tulip", "target": "Александр Манюшкин", "type": "Liked"},
    {"source": "Best Tulip", "target": "Pavel Vorontsov", "type": "Liked"},
    {"source": "Best Tulip", "target": "Edmund Tsaturyan", "type": "Liked"},
    {"source": "Best Tulip", "target": "Nastya Menshikova", "type": "Liked"},
    {"source": "Best Tulip", "target": "Anastasia Belova", "type": "Liked"},
    {"source": "Best Tulip", "target": "Роман Оленник", "type": "Liked"},                
    {"source": "Best Tulip", "target": "Evgeny Ezopov", "type": "Liked"},
    {"source": "Best Tulip", "target": "Dmitry DS", "type": "Liked"},
    {"source": "Best Tulip", "target": "Boris Love", "type": "Liked"},
    {"source": "Best Tulip", "target": "Rubel Hasan", "type": "Liked"},
    {"source": "Sasha Maksimoff", "target": "Boris Love", "type": "Liked"},  
    {"source": "Boris Love", "target": "Brandon Mubala", "type": "Liked"},
    {"source": "Boris Love", "target": "Adam Anangisye", "type": "Liked"},
    {"source": "Rubel Hasan", "target": "Ruben Renner", "type": "Liked"},   
    {"source": "Rubel Hasan", "target": "Anh Van", "type": "Liked"},
    {"source": "Rubel Hasan", "target": "Anh", "type": "Liked"},
    {"source": "Rubel Hasan", "target": "Kelly France", "type": "Liked"},
    {"source": "Rubel Hasan", "target": "Giambrone Limoncello", "type": "Liked"},
    {"source": "Rubel Hasan", "target": "Otis Davis", "type": "Liked"},
    {"source": "Dmitry DS", "target": "Boris Love", "type": "Liked"}
  ]
}
